celi_framework/core/celi_update_callback.py
celi_framework/core/job_description.py
celi_framework/core/mt_factory.py
celi_framework/core/processor.py
celi_framework/core/runner.py
celi_framework/core/section_processor.py
celi_framework/core/server.py
celi_framework/core/websocket/streams.py
celi_framework/examples/AP_English_Language/data/reference/2303.08774v6.pdf
celi_framework/examples/AP_English_Language/data/sample_questions/2023/ap23-frq-english-language-set-1.pdf
celi_framework/examples/AP_English_Language/data/sample_questions/2023/ap23-frq-english-language-set-2.pdf
celi_framework/examples/AP_English_Language/data/sample_questions/2023/set_1_clean.md
celi_framework/examples/AP_English_Language/data/sample_questions/2023/set_2.txt
celi_framework/examples/AP_English_Language/data/sample_responses/2023/ap23-apc-english-language-q1-set-1.pdf
celi_framework/examples/AP_English_Language/data/sample_responses/2023/ap23-apc-english-language-q1-set-2.pdf
celi_framework/examples/AP_English_Language/data/sample_responses/2023/ap23-apc-english-language-q2-set-1.pdf
celi_framework/examples/AP_English_Language/data/sample_responses/2023/ap23-apc-english-language-q2-set-2.pdf
celi_framework/examples/AP_English_Language/data/sample_responses/2023/ap23-apc-english-language-q3-set-1.pdf
celi_framework/examples/AP_English_Language/data/sample_responses/2023/ap23-apc-english-language-q3-set-2.pdf
celi_framework/examples/AP_English_Language/data/sample_responses/2023/set_1_q3_responses.txt
celi_framework/examples/AP_English_Language/data/sample_responses/2023/set_2_q1_responses.txt
celi_framework/examples/AP_English_Language/data/scoring_guidelines/2023/ap23-sg-english-language-set-1.pdf
celi_framework/examples/AP_English_Language/data/scoring_guidelines/2023/ap23-sg-english-language-set-2.pdf
celi_framework/examples/AP_English_Language/data/scoring_guidelines/2023/set_1_target_q1_scoring.txt
celi_framework-0.3.7.dist-info/LICENSE
celi_framework-0.3.7.dist-info/METADATA
celi_framework-0.3.7.dist-info/WHEEL
celi_framework-0.3.7.dist-info/RECORD
