Metadata-Version: 2.1
Name: celi-framework
Version: 0.3.7
Summary: Controller-Embedded Language Interactions - facilitates the entire lifecycle of document processing, from pre-processing and embedding to post-monitoring and quality assessment.
Home-page: https://github.com/x3n0cr4735/celi
License: MIT
Author: Jan-Samuel Wagner
Author-email: jwab@genmab.com
Requires-Python: >=3.10,<4.0
Classifier: Development Status :: 2 - Pre-Alpha
Classifier: Intended Audience :: Developers
Classifier: License :: OSI Approved :: MIT License
Classifier: Operating System :: OS Independent
Classifier: Programming Language :: Python :: 3
Classifier: Programming Language :: Python :: 3.10
Classifier: Programming Language :: Python :: 3.11
Classifier: Programming Language :: Python :: 3.12
Classifier: Topic :: Scientific/Engineering :: Artificial Intelligence
Classifier: Typing :: Typed
Provides-Extra: experimental
Provides-Extra: wikipedia
Requires-Dist: aioboto3 (>=13.1.1,<14.0.0)
Requires-Dist: aiosqlite (>=0.20.0)
Requires-Dist: anthropic[bedrock] (>=0.34.2,<0.35.0)
Requires-Dist: bert-score (>=0.3.13) ; extra == "experimental"
Requires-Dist: evaluate (>=0.4.1) ; extra == "experimental"
Requires-Dist: llama-index (>=0.10.23) ; extra == "wikipedia"
Requires-Dist: llama-index-vector-stores-chroma (>=0.1.6) ; extra == "wikipedia"
Requires-Dist: numpy (>=1.22.4)
Requires-Dist: openai (>=1.46.0)
Requires-Dist: opentelemetry-proto (>=1.24.0) ; extra == "experimental"
Requires-Dist: pandas (>=2.0.3)
Requires-Dist: py-llm-core (>=2.8.2) ; extra == "experimental"
Requires-Dist: pydantic (>=2.0.1)
Requires-Dist: pymongo (>=4.6.2) ; extra == "experimental"
Requires-Dist: pymupdf (>=1.24.1) ; extra == "experimental"
Requires-Dist: python-docx (>=1.1.0) ; extra == "experimental"
Requires-Dist: python-dotenv (>=1.0.0)
Requires-Dist: python-levenshtein (>=0.25.1)
Requires-Dist: requests (>=2.26.0)
Requires-Dist: requests-cache (>=1.2.0) ; extra == "experimental"
Requires-Dist: scikit-learn (>=1.4.2) ; extra == "experimental"
Project-URL: Repository, https://github.com/x3n0cr4735/celi
